[{"PlayerName":"Quinton de Kockʠ","Venue":"Dubai","Date":"Nov 5 2020","Run":"40","Bowls":"25","Fours":"5","Sixes":"1","StrikeRate":"160.00","OpponentTeamName":"Delhi Capitals","Result":"Mum Indians won by 57 runs"},{"PlayerName":"Quinton de Kockʠ","Venue":"Dubai","Date":"Nov 10 2020","Run":"20","Bowls":"12","Fours":"3","Sixes":"1","StrikeRate":"166.66","OpponentTeamName":"Delhi Capitals","Result":"Mum Indians won by 5 wickets (with 8 balls remaining)"},{"PlayerName":"Quinton de Kockʠ","Venue":"Sharjah","Date":"Nov 3 2020","Run":"25","Bowls":"13","Fours":"2","Sixes":"2","StrikeRate":"192.30","OpponentTeamName":"Sunrisers Hyderabad","Result":"Sunrisers won by 10 wickets (with 17 balls remaining)"},{"PlayerName":"Quinton de Kockʠ","Venue":"Abu Dhabi","Date":"Oct 11 2020","Run":"53","Bowls":"36","Fours":"4","Sixes":"3","StrikeRate":"147.22","OpponentTeamName":"Delhi Capitals","Result":"Mum Indians won by 5 wickets (with 2 balls remaining)"},{"PlayerName":"Quinton de Kockʠ","Venue":"Abu Dhabi","Date":"Oct 16 2020","Run":"78","Bowls":"44","Fours":"9","Sixes":"3","StrikeRate":"177.27","OpponentTeamName":"Kolkata Knight Riders","Result":"Mum Indians won by 8 wickets (with 19 balls remaining)"},{"PlayerName":"Quinton de Kockʠ","Venue":"Abu Dhabi","Date":"Oct 28 2020","Run":"18","Bowls":"19","Fours":"0","Sixes":"1","StrikeRate":"94.73","OpponentTeamName":"Royal Challengers Bangalore","Result":"Mum Indians won by 5 wickets (with 5 balls remaining)"},{"PlayerName":"Quinton de Kockʠ","Venue":"Sharjah","Date":"Oct 4 2020","Run":"67","Bowls":"39","Fours":"4","Sixes":"4","StrikeRate":"171.79","OpponentTeamName":"Sunrisers Hyderabad","Result":"Mum Indians won by 34 runs"},{"PlayerName":"Quinton de Kockʠ","Venue":"Dubai","Date":"Sep 28 2020","Run":"14","Bowls":"15","Fours":"1","Sixes":"0","StrikeRate":"93.33","OpponentTeamName":"Royal Challengers Bangalore","Result":"Match tied (RCB won the one-over eliminator)"},{"PlayerName":"Quinton de Kockʠ","Venue":"Dubai","Date":"Oct 31 2020","Run":"26","Bowls":"28","Fours":"2","Sixes":"0","StrikeRate":"92.85","OpponentTeamName":"Delhi Capitals","Result":"Mum Indians won by 9 wickets (with 34 balls remaining)"},{"PlayerName":"Quinton de Kockʠ","Venue":"Abu Dhabi","Date":"Oct 25 2020","Run":"6","Bowls":"4","Fours":"0","Sixes":"1","StrikeRate":"150.00","OpponentTeamName":"Rajasthan Royals","Result":"Royals won by 8 wickets (with 10 balls remaining)"},{"PlayerName":"Quinton de Kockʠ","Venue":"Sharjah","Date":"Oct 23 2020","Run":"46","Bowls":"37","Fours":"5","Sixes":"2","StrikeRate":"124.32","OpponentTeamName":"Chennai Super Kings","Result":"Mum Indians won by 10 wickets (with 46 balls remaining)"},{"PlayerName":"Quinton de Kockʠ","Venue":"Abu Dhabi","Date":"Sep 19 2020","Run":"33","Bowls":"20","Fours":"5","Sixes":"0","StrikeRate":"165.00","OpponentTeamName":"Chennai Super Kings","Result":"Super Kings won by 5 wickets (with 4 balls remaining)"},{"PlayerName":"Quinton de Kockʠ","Venue":"Abu Dhabi","Date":"Oct 6 2020","Run":"23","Bowls":"15","Fours":"3","Sixes":"1","StrikeRate":"153.33","OpponentTeamName":"Rajasthan Royals","Result":"Mum Indians won by 57 runs"},{"PlayerName":"Quinton de Kockʠ","Venue":"Abu Dhabi","Date":"Sep 23 2020","Run":"1","Bowls":"3","Fours":"0","Sixes":"0","StrikeRate":"33.33","OpponentTeamName":"Kolkata Knight Riders","Result":"Mum Indians won by 49 runs"},{"PlayerName":"Quinton de Kockʠ","Venue":"Abu Dhabi","Date":"Oct 1 2020","Run":"0","Bowls":"5","Fours":"0","Sixes":"0","StrikeRate":"0.00","OpponentTeamName":"Kings XI Punjab","Result":"Mum Indians won by 48 runs"},{"PlayerName":"Quinton de Kockʠ","Venue":"Dubai","Date":"Oct 18 2020","Run":"53","Bowls":"43","Fours":"3","Sixes":"3","StrikeRate":"123.25","OpponentTeamName":"Kings XI Punjab","Result":"Match tied (Kings XI won the one-over eliminator)"}]